ucp/__init__.py
ucp/__pycache__/__init__.cpython-312.pyc
ucp/_core.cpython-312-x86_64-linux-gnu.so
ucp_core-0.1.5.dist-info/METADATA
ucp_core-0.1.5.dist-info/WHEEL
ucp_core-0.1.5.dist-info/RECORD
