Metadata-Version: 2.4
Name: ucp-core
Version: 0.1.5
Classifier: Development Status :: 4 - Beta
Classifier: Programming Language :: Rust
Classifier: Programming Language :: Python :: Implementation :: CPython
Classifier: Programming Language :: Python :: 3.8
Classifier: Programming Language :: Python :: 3.9
Classifier: Programming Language :: Python :: 3.10
Classifier: Programming Language :: Python :: 3.11
Classifier: Programming Language :: Python :: 3.12
Classifier: Topic :: Text Processing :: Markup
Summary: Python bindings for UCP (Unified Content Protocol) - Rust implementation
Keywords: ucp,content,document,markdown,structured
Author: UCP Contributors
License: MIT
Requires-Python: >=3.8
Project-URL: Documentation, https://github.com/unified-content/ucp
Project-URL: Homepage, https://github.com/unified-content/ucp
Project-URL: Repository, https://github.com/unified-content/ucp
